{
 "color": "#10e396",
 "creation": "2023-12-02 13:23:25.414364",
 "docstatus": 0,
 "doctype": "Number Card",
 "filters_json": "{\"date\":\"2023-12-02\",\"lead\":1,\"quotation\":1}",
 "function": "Count",
 "idx": 0,
 "is_public": 1,
 "is_standard": 1,
 "label": "Today Followed Lead / Quotation Count",
 "modified": "2023-12-02 13:30:33.816296",
 "modified_by": "Administrator",
 "module": "Global Safety Enterprises",
 "name": "Today Followed Lead Quotation Count",
 "owner": "Administrator",
 "report_field": "for_number_card",
 "report_function": "Sum",
 "report_name": "Daily Follow Up Status",
 "show_percentage_stats": 1,
 "stats_time_interval": "Daily",
 "type": "Report"
}