{
 "attach_print": 0,
 "channel": "Slack",
 "creation": "2024-01-26 12:33:55.707891",
 "days_in_advance": 0,
 "docstatus": 0,
 "doctype": "Notification",
 "document_type": "Quotation",
 "enabled": 1,
 "event": "Save",
 "idx": 0,
 "is_standard": 1,
 "message": "Quotation {{ doc.name }} was created at {{ doc.creation }}\n\nQuotation Owner: {{ doc.get(\"custom_quotation_owner\") }}\n\nAmount: {{ doc.rounded_total }}",
 "modified": "2024-01-26 18:02:41.185024",
 "modified_by": "Administrator",
 "module": "Global Safety Enterprises",
 "name": "Quotation Created",
 "owner": "Administrator",
 "recipients": [],
 "send_system_notification": 1,
 "send_to_all_assignees": 0,
 "slack_webhook_url": "Slack Notification",
 "subject": "Quotation Created"
}